prodict/__init__.py
prodict-0.8.22.dist-info/METADATA
prodict-0.8.22.dist-info/WHEEL
prodict-0.8.22.dist-info/licenses/LICENSE.txt
prodict-0.8.22.dist-info/RECORD
