Metadata-Version: 2.4
Name: prodict
Version: 0.8.22
Summary: Prodict = Pro Dictionary with IDE friendly(auto code completion), dot-accessible attributes and more.
Project-URL: Homepage, https://github.com/ramazanpolat/prodict
Project-URL: Download, https://pypi.python.org/pypi/prodict/0.8.22
Project-URL: Repository, https://github.com/ramazanpolat/prodict
Project-URL: Issues, https://github.com/ramazanpolat/prodict/issues
Author-email: Ramazan Polat <ramazanpolat@gmail.com>
License: MIT
License-File: LICENSE.txt
Keywords: auto-code-complete,auto-complete,dict,dictionary,dynamic-props,prodict,python3,typehinting
Classifier: Development Status :: 4 - Beta
Classifier: Intended Audience :: Developers
Classifier: License :: OSI Approved :: MIT License
Classifier: Programming Language :: Python :: 3.12
Classifier: Topic :: Software Development :: Libraries :: Python Modules
Requires-Python: >=3.7
Provides-Extra: dev
Requires-Dist: pytest>=7.0.0; extra == 'dev'
